{"flow":"tally_onboarding","flowState":{"goal":{"classification":"internal","type":"string"}},"initial":"tally_welcome","minClient":1,"schemaVersion":1,"screenArtifacts":{"tally_debt":{"contentHash":"sha256:0b7044939232695466ea495135a1fb2f0631a7563a8f6c90822f58481ae5c8e9","minClient":1,"path":"tally_debt.rfw","schemaVersion":1,"version":1},"tally_goal":{"contentHash":"sha256:fe933e340510619e92c9c381cbeb8fa1fd0380be066a70f68e29666e4ac128e7","minClient":1,"path":"tally_goal.rfw","schemaVersion":1,"version":1},"tally_invest":{"contentHash":"sha256:e3332b4f148439fa6adc9e1bcfc7434ae7edc27f7768bba4aec206a84f7464ef","minClient":1,"path":"tally_invest.rfw","schemaVersion":1,"version":1},"tally_recap_debt":{"contentHash":"sha256:b0a64c9e84db2b2e9ff465a9ea756b41b0806bd22eac9b3689363780fdbced5c","minClient":1,"path":"tally_recap_debt.rfw","schemaVersion":1,"version":1},"tally_recap_invest":{"contentHash":"sha256:afca3cf383795539c21dad7661282f5d8140369f0a1c90fb956aedc76f6f58d8","minClient":1,"path":"tally_recap_invest.rfw","schemaVersion":1,"version":1},"tally_recap_savings":{"contentHash":"sha256:40da3c3d6e16a09722decbe67dce0e9ba05df47bc82416203124e1936bd8a929","minClient":1,"path":"tally_recap_savings.rfw","schemaVersion":1,"version":1},"tally_savings":{"contentHash":"sha256:228ec9e00d6d7177799cf446463ad9cf5ad8fee7bd8d45ff12334c8f069c4553","minClient":1,"path":"tally_savings.rfw","schemaVersion":1,"version":1},"tally_welcome":{"contentHash":"sha256:217fce26e9f8a4a7b7d205edf51e1dd3a313f942b91384523a75f49eaac03106","minClient":1,"path":"tally_welcome.rfw","schemaVersion":1,"version":1}},"states":{"done":{"kind":"end","result":{}},"route":{"branches":[{"goto":"tally_recap_debt","when":{"goal":{"eq":{"literal":"debt","type":"string"}}}},{"goto":"tally_recap_savings","when":{"goal":{"eq":{"literal":"savings","type":"string"}}}}],"default":{"goto":"tally_recap_invest"},"kind":"decision"},"tally_debt":{"kind":"screen","on":{"next":{"target":"route","type":"goto"}},"screen":"tally_debt"},"tally_goal":{"kind":"screen","on":{"debt":{"set":{"goal":{"type":"string","value":{"literal":"debt","type":"string"}}},"target":"tally_debt","type":"goto"},"invest":{"set":{"goal":{"type":"string","value":{"literal":"invest","type":"string"}}},"target":"tally_invest","type":"goto"},"savings":{"set":{"goal":{"type":"string","value":{"literal":"savings","type":"string"}}},"target":"tally_savings","type":"goto"}},"screen":"tally_goal"},"tally_invest":{"kind":"screen","on":{"next":{"target":"route","type":"goto"}},"screen":"tally_invest"},"tally_recap_debt":{"kind":"screen","on":{"finish":{"target":"done","type":"goto"}},"screen":"tally_recap_debt"},"tally_recap_invest":{"kind":"screen","on":{"finish":{"target":"done","type":"goto"}},"screen":"tally_recap_invest"},"tally_recap_savings":{"kind":"screen","on":{"finish":{"target":"done","type":"goto"}},"screen":"tally_recap_savings"},"tally_savings":{"kind":"screen","on":{"next":{"target":"route","type":"goto"}},"screen":"tally_savings"},"tally_welcome":{"kind":"screen","on":{"start":{"target":"tally_goal","type":"goto"}},"screen":"tally_welcome"}},"version":1}